odoo/addons/stock_restrict_lot/README.rst
odoo/addons/stock_restrict_lot/__init__.py
odoo/addons/stock_restrict_lot/__manifest__.py
odoo/addons/stock_restrict_lot/i18n/es.po
odoo/addons/stock_restrict_lot/i18n/hr.po
odoo/addons/stock_restrict_lot/i18n/it.po
odoo/addons/stock_restrict_lot/i18n/nl.po
odoo/addons/stock_restrict_lot/i18n/nl_NL.po
odoo/addons/stock_restrict_lot/i18n/pt.po
odoo/addons/stock_restrict_lot/i18n/pt_BR.po
odoo/addons/stock_restrict_lot/i18n/stock_restrict_lot.pot
odoo/addons/stock_restrict_lot/models/__init__.py
odoo/addons/stock_restrict_lot/models/product_product.py
odoo/addons/stock_restrict_lot/models/stock_move.py
odoo/addons/stock_restrict_lot/models/stock_picking.py
odoo/addons/stock_restrict_lot/models/stock_rule.py
odoo/addons/stock_restrict_lot/readme/CONTRIBUTORS.md
odoo/addons/stock_restrict_lot/readme/DESCRIPTION.md
odoo/addons/stock_restrict_lot/static/description/icon.png
odoo/addons/stock_restrict_lot/static/description/index.html
odoo/addons/stock_restrict_lot/tests/__init__.py
odoo/addons/stock_restrict_lot/tests/test_restrict_lot.py
odoo/addons/stock_restrict_lot/views/stock_move_views.xml
odoo/addons/stock_restrict_lot/views/stock_picking.xml
odoo_addon_stock_restrict_lot-18.0.1.1.0.dist-info/METADATA
odoo_addon_stock_restrict_lot-18.0.1.1.0.dist-info/WHEEL
odoo_addon_stock_restrict_lot-18.0.1.1.0.dist-info/top_level.txt
odoo_addon_stock_restrict_lot-18.0.1.1.0.dist-info/RECORD
