Metadata-Version: 2.1
Name: odoo-addon-stock_restrict_lot
Version: 18.0.1.1.0
Requires-Python: >=3.10
Requires-Dist: odoo==18.0.*
Summary: Base module that add back the concept of restrict lot on stock move
Home-page: https://github.com/OCA/stock-logistics-workflow
License: LGPL-3
Author: Akretion, Odoo Community Association (OCA)
Author-email: support@odoo-community.org
Classifier: Programming Language :: Python
Classifier: Framework :: Odoo
Classifier: Framework :: Odoo :: 18.0
Classifier: License :: OSI Approved :: GNU Lesser General Public License v3 (LGPLv3)
